auto_mlflow/__init__.py
auto_mlflow-1.5.dist-info/METADATA
auto_mlflow-1.5.dist-info/WHEEL
auto_mlflow-1.5.dist-info/top_level.txt
auto_mlflow-1.5.dist-info/RECORD
