Metadata-Version: 2.1
Name: auto_mlflow
Version: 1.5
Summary: Auto MLFlow is an open-source automated MLOps library for MLFlow in Python. While MLFlow provides a UI for tracking experiments, Auto MLFlow automates and simplifies the logging process, reducing manual effort and ensuring seamless integration with ML workflows.
Home-page: http://github.com/mr-ravin/auto_mlflow
Author: Ravin Kumar
Author-email: mr.ravin_kumar@hotmail.com
Keywords: MLFlow,MLOps,Deep Learning,Automation,Deployment,Deep Learning,Architecture
Classifier: Programming Language :: Python :: 3
Classifier: License :: OSI Approved :: MIT License
Classifier: Operating System :: OS Independent
Requires-Python: >=3.8,<3.13
Requires-Dist: mlflow <=2.20.3,>=2.9.2
Requires-Dist: opencv-contrib-python >=4.7.0.72
Requires-Dist: opencv-python >=4.7.0.72
Requires-Dist: opencv-python-headless >=4.8.0.74
